Metadata-Version: 2.1
Name: biostructmap
Version: 0.4.1
Summary: A package for mapping biological data onto protein PDB structures
Home-page: https://github.com/andrewguy/biostructmap
Author: Andrew Guy
Author-email: andrewjguy42@gmail.com
License: UNKNOWN
Download-URL: https://github.com/andrewguy/biostructmap/archive/refs/tags/0.4.1.tar.gz
Platform: any
Classifier: Programming Language :: Python
Classifier: Development Status :: 4 - Beta
Classifier: Natural Language :: English
Classifier: Intended Audience :: Science/Research
Classifier: License :: OSI Approved :: MIT License
Classifier: Operating System :: OS Independent
Classifier: Topic :: Scientific/Engineering :: Bio-Informatics
Provides-Extra: testing
